LICENSE
MANIFEST.in
README.rst
setup.py
django_requestrepeat.egg-info/PKG-INFO
django_requestrepeat.egg-info/SOURCES.txt
django_requestrepeat.egg-info/dependency_links.txt
django_requestrepeat.egg-info/requires.txt
django_requestrepeat.egg-info/top_level.txt
requestrepeat/__init__.py
requestrepeat/admin.py
requestrepeat/models.py
requestrepeat/repeat.py
requestrepeat/tests.py
requestrepeat/migrations/__init__.py
requestrepeat/rr/__init__.py
requestrepeat/rr/admin.py
requestrepeat/rr/models.py
requestrepeat/rr/repeat.py
requestrepeat/rr/tests.py