Metadata-Version: 1.0
Name: django-requestrepeat
Version: 0.5
Summary: A django app that repeats one http POST into several.
Home-page: https://github.com/clickyspinny/django-requestrepeat/tree/master/requestrepeat
Author: Oceana Technologies
Author-email: ben@oceanatech.com
License: BSD License
Platform: UNKNOWN
